snlp/__init__.py
snlp/gaussianize.py
snlp/evaluation/__init__.py
snlp/evaluation/functions.py
snlp/evaluation/metrics.py
snlp/mwes/__init__.py
snlp/mwes/am.py
snlp/mwes/mwe.py
snlp/mwes/mwe_utils.py
snlp/preprocessing/__init__.py
snlp/preprocessing/cleaning.py
snlp/preprocessing/filtering.py
snlp/test/__init__.py
snlp/test/test_am.py
snlp/text_analysis/__init__.py
snlp/text_analysis/visual_analysis.py
snlp-0.1.3.post4.data/scripts/downloads.py
snlp-0.1.3.post4.dist-info/LICENSE
snlp-0.1.3.post4.dist-info/METADATA
snlp-0.1.3.post4.dist-info/WHEEL
snlp-0.1.3.post4.dist-info/top_level.txt
snlp-0.1.3.post4.dist-info/RECORD
