Metadata-Version: 2.1
Name: snlp
Version: 0.1.3.post4
Summary: Statistical NLP
Home-page: https://github.com/meghdadFar/snlp
Author: meghdadFar
Author-email: meghdad.farahmand@gmail.com
License: UNKNOWN
Platform: UNKNOWN
Requires-Python: >=3.7
Requires-Dist: pandas (==1.2.3)
Requires-Dist: scikit-learn (==0.22.2.post1)
Requires-Dist: scipy (==1.4.1)
Requires-Dist: nltk (>=3.6.2)
Requires-Dist: tqdm (==4.45.0)
Requires-Dist: wordcloud (==1.7.0)
Requires-Dist: plotly (==5.1.0)
